{
  "project_info": {
    "project_number": "775995923163",
    "project_id": "my-application12-bfe73",
    "storage_bucket": "my-application12-bfe73.appspot.com"
  },
  "client": [
    {
      "client_info": {
        "mobilesdk_app_id": "1:775995923163:android:23c15496644e84b9510afe",
        "android_client_info": {
          "package_name": "com.example.myapplication"
        }
      },
      "oauth_client": [
        {
          "client_id": "775995923163-6vo6d27h9602c6rvdoj8583p2oko2tto.apps.googleusercontent.com",
          "client_type": 3
        }
      ],
      "api_key": [
        {
          "current_key": "AIzaSyBDcQMDKEfibMH2xQypFEnGQa_0RaCldIU"
        }
      ],
      "services": {
        "appinvite_service": {
          "other_platform_oauth_client": [
            {
              "client_id": "775995923163-6vo6d27h9602c6rvdoj8583p2oko2tto.apps.googleusercontent.com",
              "client_type": 3
            }
          ]
        }
      }
    }
  ],
  "configuration_version": "1"
}